{
	"m_CorrespondingSourceObject": { "m_Collection": "cab-2e6cf2619083e464c332a7a5e8898e10", "m_PathID": 0 },
	"m_EditorClassIdentifier": "",
	"m_EditorHideFlags": 0,
	"m_Enabled": 1,
	"m_GameObject": { "m_Collection": "cab-2e6cf2619083e464c332a7a5e8898e10", "m_PathID": 0 },
	"m_HideFlags": 0,
	"m_Name": "cha_0480202.fadeMotionList",
	"m_PrefabAsset": { "m_Collection": "cab-2e6cf2619083e464c332a7a5e8898e10", "m_PathID": 0 },
	"m_PrefabInstance": { "m_Collection": "cab-2e6cf2619083e464c332a7a5e8898e10", "m_PathID": 0 },
	"m_Script": { "m_Collection": "cab-2e6cf2619083e464c332a7a5e8898e10", "m_PathID": -5701686848450234253 },
	"m_Structure": {
		"MotionInstanceIds": [
			751550,
			751554,
			751552
		],
		"CubismFadeMotionObjects": [
			{ "m_Collection": "cab-2e6cf2619083e464c332a7a5e8898e10", "m_PathID": 2069872899259644530 },
			{ "m_Collection": "cab-2e6cf2619083e464c332a7a5e8898e10", "m_PathID": -2277030555639317591 },
			{ "m_Collection": "cab-2e6cf2619083e464c332a7a5e8898e10", "m_PathID": 2478148202913275670 }
		]
	}
}